curricula_grade_cpp/__init__.py
curricula_grade_cpp/version.py
curricula_grade_cpp/gtest/gtest.cpp
curricula_grade_cpp/include/curricula.hpp
curricula_grade_cpp/include/curricula/random.hpp
curricula_grade_cpp/include/curricula/sort.hpp
curricula_grade_cpp/setup/__init__.py
curricula_grade_cpp/setup/common/__init__.py
curricula_grade_cpp/setup/common/gpp.py
curricula_grade_cpp/setup/common/makefile.py
curricula_grade_cpp/test/__init__.py
curricula_grade_cpp/test/correctness/__init__.py
curricula_grade_cpp/test/correctness/common.py
curricula_grade_cpp-2.1.0.dist-info/METADATA
curricula_grade_cpp-2.1.0.dist-info/WHEEL
curricula_grade_cpp-2.1.0.dist-info/top_level.txt
curricula_grade_cpp-2.1.0.dist-info/RECORD
