Metadata-Version: 2.1
Name: curricula-grade-cpp
Version: 2.1.0
Summary: A set of grading addons specific to C++
Home-page: https://github.com/curriculagg/curricula-grade-cpp
Author: Noah Kim
Author-email: noahbkim@gmail.com
License: UNKNOWN
Platform: UNKNOWN
Requires-Python: >=3.9
Requires-Dist: curricula (~=2.1.0)
Requires-Dist: curricula-grade (~=2.1.0)
